mozen_zoo/__init__.py
mozen_zoo/demo.py
mozen_zoo/models.py
mozen_zoo-1.4.0.dist-info/METADATA
mozen_zoo-1.4.0.dist-info/WHEEL
mozen_zoo-1.4.0.dist-info/top_level.txt
mozen_zoo-1.4.0.dist-info/RECORD
