Metadata-Version: 2.1
Name: mozen-zoo
Version: 1.4.0
Summary: Python library of Mozen web site
Home-page: https://gitlab.lis-lab.fr/augustin.sambou/mozen.git
Author: SAMBOU Augustin
Author-email: aniamba-amaye.sambou@etu.univ-amu.fr
License: UNKNOWN
Platform: UNKNOWN
Classifier: Programming Language :: Python :: 3
Classifier: License :: OSI Approved :: MIT License
Classifier: Operating System :: OS Independent
Requires-Python: >=3.6
